intersystems_irispython.libs/libcrypto-c303ee8a.so.3
intersystems_irispython.libs/libelsdkcore-4ffab039.so
intersystems_irispython.libs/libirisconnect-03c350cf.so
intersystems_irispython.libs/libssl-de490988.so.3
iris/_Callback.py
iris/_GatewayEvent.py
iris/_GatewayUtility.py
iris/_IRISGlobalNode.py
iris/_IRISGlobalNodeView.py
iris/_IRISIterator.py
iris/_LegacyIterator.py
iris/_ModuleBank.py
iris/_PrintStream.py
iris/__init__.py
iris/__main__.py
iris/_elsdk_.py
iris/irissdk.cpython-310-x86_64-linux-gnu.so
iris/irissdk.cpython-311-x86_64-linux-gnu.so
iris/irissdk.cpython-312-x86_64-linux-gnu.so
iris/irissdk.cpython-313-x86_64-linux-gnu.so
iris/irissdk.cpython-314-x86_64-linux-gnu.so
iris/irissdk.cpython-38-x86_64-linux-gnu.so
iris/irissdk.cpython-39-x86_64-linux-gnu.so
iris/dbapi/__init__.py
iris/pex/_BusinessHost.py
iris/pex/_BusinessOperation.py
iris/pex/_BusinessProcess.py
iris/pex/_BusinessService.py
iris/pex/_Common.py
iris/pex/_Director.py
iris/pex/_IRISBusinessOperation.py
iris/pex/_IRISBusinessService.py
iris/pex/_IRISInboundAdapter.py
iris/pex/_IRISOutboundAdapter.py
iris/pex/_InboundAdapter.py
iris/pex/_Message.py
iris/pex/_OutboundAdapter.py
iris/pex/__init__.py
irisnative/_IRISNative.py
irisnative/__init__.py
intersystems_irispython-5.3.1.dist-info/METADATA
intersystems_irispython-5.3.1.dist-info/WHEEL
intersystems_irispython-5.3.1.dist-info/top_level.txt
intersystems_irispython-5.3.1.dist-info/RECORD
intersystems_irispython-5.3.1.dist-info/licenses/LICENSE-OpenSSL.txt
intersystems_irispython-5.3.1.dist-info/licenses/LICENSE.txt
