Metadata-Version: 2.4
Name: intersystems_irispython
Version: 5.3.1
Summary: InterSystems IRIS Python SDK Kit
Author-email: InterSystems Corporation <support@intersystems.com>
License-Expression: LicenseRef-InterSystems-External-Repository
Project-URL: Homepage, https://www.intersystems.com/
Project-URL: License, https://www.intersystems.com/IERTU/
Project-URL: Documentation, https://docs.intersystems.com/irislatest/csp/docbook/DocBook.UI.Page.cls?KEY=PAGE_python_native
Classifier: Development Status :: 5 - Production/Stable
Classifier: Topic :: Database
Classifier: Topic :: Database :: Front-Ends
Classifier: Programming Language :: Python :: 3
Classifier: Programming Language :: Python :: 3 :: Only
Classifier: Programming Language :: Python :: 3.8
Classifier: Programming Language :: Python :: 3.9
Classifier: Programming Language :: Python :: 3.10
Classifier: Programming Language :: Python :: 3.11
Classifier: Programming Language :: Python :: 3.12
Classifier: Programming Language :: Python :: 3.13
Classifier: Programming Language :: Python :: 3.14
Classifier: Programming Language :: Python :: Implementation :: CPython
Classifier: Operating System :: MacOS :: MacOS X
Classifier: Operating System :: Microsoft :: Windows
Classifier: Operating System :: POSIX :: Linux
Requires-Python: >=3.8
License-File: LICENSE-OpenSSL.txt
License-File: LICENSE.txt
Dynamic: license-file
